app/__init__.py
app/add.py
app/cli.py
app/config.py
app/types_.py
markdown_timesheet-0.6.dist-info/LICENSE
markdown_timesheet-0.6.dist-info/METADATA
markdown_timesheet-0.6.dist-info/WHEEL
markdown_timesheet-0.6.dist-info/entry_points.txt
markdown_timesheet-0.6.dist-info/top_level.txt
markdown_timesheet-0.6.dist-info/RECORD
