Metadata-Version: 2.1
Name: markdown-timesheet
Version: 0.6
Summary: CLI to add up time entries in a Markdown file.
Home-page: https://github.com/zevaverbach/markdown_timesheet
Author: Zev Averbach
Author-email: zev@averba.ch
License: MIT license
Keywords: markdown timesheet
Platform: UNKNOWN
Classifier: Development Status :: 2 - Pre-Alpha
Classifier: Intended Audience :: Developers
Classifier: License :: OSI Approved :: MIT License
Classifier: Natural Language :: English
Classifier: Programming Language :: Python :: 3.5
Classifier: Programming Language :: Python :: 3.6
Classifier: Programming Language :: Python :: 3.7
